terrible/__init__.py
terrible/cli.py
terrible/terrible.py
terrible-0.1.2.dist-info/DESCRIPTION.rst
terrible-0.1.2.dist-info/METADATA
terrible-0.1.2.dist-info/RECORD
terrible-0.1.2.dist-info/WHEEL
terrible-0.1.2.dist-info/entry_points.txt
terrible-0.1.2.dist-info/metadata.json
terrible-0.1.2.dist-info/top_level.txt
