Metadata-Version: 2.0
Name: terrible
Version: 0.1.2
Summary: Ansible dynamic inventory from Terraform
Home-page: https://github.com/palmertime/terrible
Author: Michael J. Palmer
Author-email: palmertime@gmail.com
License: Apache Software License 2.0
Keywords: terrible
Platform: UNKNOWN
Classifier: Development Status :: 2 - Pre-Alpha
Classifier: Intended Audience :: Developers
Classifier: License :: OSI Approved :: Apache Software License
Classifier: Natural Language :: English
Classifier: Programming Language :: Python :: 2
Classifier: Programming Language :: Python :: 2.6
Classifier: Programming Language :: Python :: 2.7
Classifier: Programming Language :: Python :: 3
Classifier: Programming Language :: Python :: 3.3
Classifier: Programming Language :: Python :: 3.4
Classifier: Programming Language :: Python :: 3.5
Classifier: Programming Language :: Python :: 3.6
Requires-Dist: Click (>=6.0)
